gbwog/panel/.git-easy-crypt-key
gbwog/panel/CurrencyRoulette.py
gbwog/panel/Game.py
gbwog/panel/GuessGame.py
gbwog/panel/Live.py
gbwog/panel/MainGame.py
gbwog/panel/MemoryGame.py
gbwog/panel/Score.py
gbwog/panel/Utils.py
gbwog/panel/__init__.py
gbwog/panel/curr.key.sec
gbwog.panel-1.1.0.dist-info/LICENSE
gbwog.panel-1.1.0.dist-info/METADATA
gbwog.panel-1.1.0.dist-info/WHEEL
gbwog.panel-1.1.0.dist-info/top_level.txt
gbwog.panel-1.1.0.dist-info/RECORD
