Metadata-Version: 2.1
Name: gbwog.panel
Version: 1.1.0
Summary: DevOpsCourse Project
Home-page: https://github.com/gboimel98/WorldOfGames
Author: GalB
Author-email: gboimel98@gmail.com
License: UNKNOWN
Platform: UNKNOWN
Classifier: Programming Language :: Python :: 3
Classifier: License :: OSI Approved :: MIT License
Classifier: Operating System :: OS Independent
Requires-Python: >=3.6
Requires-Dist: git-easy-crypt
Requires-Dist: requests
Requires-Dist: flask
Requires-Dist: airium
